setup.py
pyFarnell/__init__.py
pyFarnell/pyFarnell.py
pyFarnell.egg-info/PKG-INFO
pyFarnell.egg-info/SOURCES.txt
pyFarnell.egg-info/dependency_links.txt
pyFarnell.egg-info/requires.txt
pyFarnell.egg-info/top_level.txt