Metadata-Version: 1.1
Name: pyFarnell
Version: 0.1.0.dev6
Summary: Connect to Farnell REST API from Python. This is absolutely NOT OFFICIAL package!!
Home-page: http://www.github.com/hecko/pyFarnell
Author: Marcel Hecko
Author-email: maco@blava.net
License: UNKNOWN
Platform: UNKNOWN
Classifier: Development Status :: 3 - Alpha
Classifier: Programming Language :: Python :: 2.7
